vern/__init__.py
vern/misc.py
vern/parse_all.py
vern/parse_autocad.py
vern/parse_mat.py
vern/parse_oscilloscope.py
vern/parse_profilometer.py
vern/parse_tabular.py
vern/parse_vsm.py
vern-1.1.9.dist-info/LICENSE
vern-1.1.9.dist-info/METADATA
vern-1.1.9.dist-info/WHEEL
vern-1.1.9.dist-info/entry_points.txt
vern-1.1.9.dist-info/top_level.txt
vern-1.1.9.dist-info/RECORD
