Metadata-Version: 2.1
Name: vern
Version: 1.1.9
Summary: templated auto processing/visualization of measured data
Home-page: http://github.com/BoronSpoon/vern
Author: boronspoon
Author-email: rayanticlimactic@gmail.com
License: MIT License
Keywords: matplotlib,research,plot
Classifier: Development Status :: 5 - Production/Stable
Classifier: License :: OSI Approved :: MIT License
Classifier: Programming Language :: Python
Classifier: Programming Language :: Python :: 3
Classifier: Topic :: Scientific/Engineering :: Visualization
Classifier: Topic :: Software Development :: Libraries :: Python Modules
License-File: LICENSE
Requires-Dist: ezdxf
Requires-Dist: numpy
Requires-Dist: matplotlib
Requires-Dist: pandas
Requires-Dist: mat73
Requires-Dist: sklearn
